{"expireTime":9007200810278411000,"key":"transformer-remark-markdown-html-ast-ec1a4a48e51c9091b660b7ba186a33fc-gatsby-remark-component-","val":{"type":"root","children":[{"type":"element","tagName":"p","properties":{},"children":[{"type":"text","value":"When deciding how to approach a new website, you may be taken back by all the options you have. Even if you’ve settled on creating a static site, the number of tools available is astounding. In this article we’ll break down a couple of the popular options for generating static sites.","position":{"start":{"line":2,"column":1,"offset":1},"end":{"line":2,"column":285,"offset":285}}}],"position":{"start":{"line":2,"column":1,"offset":1},"end":{"line":2,"column":285,"offset":285}}},{"type":"text","value":"\n"},{"type":"element","tagName":"p","properties":{},"children":[{"type":"element","tagName":"a","properties":{"href":"https://jekyllrb.com/"},"children":[{"type":"text","value":"The Jekyll site generator","position":{"start":{"line":4,"column":2,"offset":288},"end":{"line":4,"column":27,"offset":313}}}],"position":{"start":{"line":4,"column":1,"offset":287},"end":{"line":4,"column":51,"offset":337}}},{"type":"text","value":" is one of the most established in the market for a couple of reasons. Firstly, it was developed by one of the founders of GitHub. On this basis alone, the thousands of developers who used GitHub for their source control were exposed to it. GitHub also used Jekyll to offer ","position":{"start":{"line":4,"column":51,"offset":337},"end":{"line":4,"column":325,"offset":611}}},{"type":"element","tagName":"a","properties":{"href":"https://pages.github.com/"},"children":[{"type":"text","value":"GitHub pages","position":{"start":{"line":4,"column":326,"offset":612},"end":{"line":4,"column":338,"offset":624}}}],"position":{"start":{"line":4,"column":325,"offset":611},"end":{"line":4,"column":366,"offset":652}}},{"type":"text","value":", a service to create free sites and blogs simply by interacting with a Git repository. This kicked off a resurgence in the popularity of static sites, especially in light of some of the security problems CMSes like WordPress or Drupal encountered.","position":{"start":{"line":4,"column":366,"offset":652},"end":{"line":4,"column":614,"offset":900}}}],"position":{"start":{"line":4,"column":1,"offset":287},"end":{"line":4,"column":614,"offset":900}}},{"type":"text","value":"\n"},{"type":"element","tagName":"p","properties":{},"children":[{"type":"text","value":"Soon after, a whole ecosystem of similar tools started popping up. Some were existing tools, like those for generating software documentation, that could easily handle generic or blogging duties as well. But developers also started creating other brand new contenders, and ","position":{"start":{"line":6,"column":1,"offset":902},"end":{"line":6,"column":274,"offset":1175}}},{"type":"element","tagName":"a","properties":{"href":"https://gohugo.io/"},"children":[{"type":"text","value":"Hugo","position":{"start":{"line":6,"column":275,"offset":1176},"end":{"line":6,"column":279,"offset":1180}}}],"position":{"start":{"line":6,"column":274,"offset":1175},"end":{"line":6,"column":300,"offset":1201}}},{"type":"text","value":" is one of the top entries on that list. It’s targeted at users who are concerned with performance, as it boasts very quick builds even for large sites.","position":{"start":{"line":6,"column":300,"offset":1201},"end":{"line":6,"column":452,"offset":1353}}}],"position":{"start":{"line":6,"column":1,"offset":902},"end":{"line":6,"column":452,"offset":1353}}},{"type":"text","value":"\n"},{"type":"element","tagName":"p","properties":{},"children":[{"type":"text","value":"Which brings us to the question at hand: what is the difference between these two applications? When comparing static site generators (SSGs), there are a couple of key attributes you can use to make your decision:","position":{"start":{"line":8,"column":1,"offset":1355},"end":{"line":8,"column":214,"offset":1568}}}],"position":{"start":{"line":8,"column":1,"offset":1355},"end":{"line":8,"column":214,"offset":1568}}},{"type":"text","value":"\n"},{"type":"element","tagName":"ol","properties":{},"children":[{"type":"text","value":"\n"},{"type":"element","tagName":"li","properties":{},"children":[{"type":"element","tagName":"strong","properties":{},"children":[{"type":"text","value":"Technology Stack:","position":{"start":{"line":10,"column":7,"offset":1576},"end":{"line":10,"column":24,"offset":1593}}}],"position":{"start":{"line":10,"column":5,"offset":1574},"end":{"line":10,"column":26,"offset":1595}}},{"type":"text","value":" The additional software needed by the SSG.","position":{"start":{"line":10,"column":26,"offset":1595},"end":{"line":10,"column":69,"offset":1638}}}],"position":{"start":{"line":10,"column":1,"offset":1570},"end":{"line":10,"column":69,"offset":1638}}},{"type":"text","value":"\n"},{"type":"element","tagName":"li","properties":{},"children":[{"type":"element","tagName":"strong","properties":{},"children":[{"type":"text","value":"Live reload:","position":{"start":{"line":11,"column":7,"offset":1645},"end":{"line":11,"column":19,"offset":1657}}}],"position":{"start":{"line":11,"column":5,"offset":1643},"end":{"line":11,"column":21,"offset":1659}}},{"type":"text","value":" The ability to reload updated content without restarting the server.","position":{"start":{"line":11,"column":21,"offset":1659},"end":{"line":11,"column":90,"offset":1728}}}],"position":{"start":{"line":11,"column":1,"offset":1639},"end":{"line":11,"column":90,"offset":1728}}},{"type":"text","value":"\n"},{"type":"element","tagName":"li","properties":{},"children":[{"type":"element","tagName":"strong","properties":{},"children":[{"type":"text","value":"Content Format(s):","position":{"start":{"line":12,"column":7,"offset":1735},"end":{"line":12,"column":25,"offset":1753}}}],"position":{"start":{"line":12,"column":5,"offset":1733},"end":{"line":12,"column":27,"offset":1755}}},{"type":"text","value":" The markup formats you can use to author content for your site.","position":{"start":{"line":12,"column":27,"offset":1755},"end":{"line":12,"column":91,"offset":1819}}}],"position":{"start":{"line":12,"column":1,"offset":1729},"end":{"line":12,"column":91,"offset":1819}}},{"type":"text","value":"\n"},{"type":"element","tagName":"li","properties":{},"children":[{"type":"element","tagName":"strong","properties":{},"children":[{"type":"text","value":"Themes & Templating:","position":{"start":{"line":13,"column":7,"offset":1826},"end":{"line":13,"column":27,"offset":1846}}}],"position":{"start":{"line":13,"column":5,"offset":1824},"end":{"line":13,"column":29,"offset":1848}}},{"type":"text","value":" Availability of installable themes, and the templating language used to create page layouts.","position":{"start":{"line":13,"column":29,"offset":1848},"end":{"line":13,"column":122,"offset":1941}}}],"position":{"start":{"line":13,"column":1,"offset":1820},"end":{"line":13,"column":122,"offset":1941}}},{"type":"text","value":"\n"},{"type":"element","tagName":"li","properties":{},"children":[{"type":"element","tagName":"strong","properties":{},"children":[{"type":"text","value":"Plug-in Support:","position":{"start":{"line":14,"column":7,"offset":1948},"end":{"line":14,"column":23,"offset":1964}}}],"position":{"start":{"line":14,"column":5,"offset":1946},"end":{"line":14,"column":25,"offset":1966}}},{"type":"text","value":" Availability of plugins providing additional functionality.","position":{"start":{"line":14,"column":25,"offset":1966},"end":{"line":14,"column":85,"offset":2026}}}],"position":{"start":{"line":14,"column":1,"offset":1942},"end":{"line":14,"column":85,"offset":2026}}},{"type":"text","value":"\n"},{"type":"element","tagName":"li","properties":{},"children":[{"type":"element","tagName":"strong","properties":{},"children":[{"type":"text","value":"Administration:","position":{"start":{"line":15,"column":7,"offset":2033},"end":{"line":15,"column":22,"offset":2048}}}],"position":{"start":{"line":15,"column":5,"offset":2031},"end":{"line":15,"column":24,"offset":2050}}},{"type":"text","value":" Availability of a compatible GUI admin interface.","position":{"start":{"line":15,"column":24,"offset":2050},"end":{"line":15,"column":74,"offset":2100}}}],"position":{"start":{"line":15,"column":1,"offset":2027},"end":{"line":15,"column":74,"offset":2100}}},{"type":"text","value":"\n"}],"position":{"start":{"line":10,"column":1,"offset":1570},"end":{"line":15,"column":74,"offset":2100}}},{"type":"text","value":"\n"},{"type":"element","tagName":"p","properties":{},"children":[{"type":"text","value":"We’ll examine both Jekyll and Hugo across all the above categories in the sections below.","position":{"start":{"line":17,"column":1,"offset":2102},"end":{"line":17,"column":90,"offset":2191}}}],"position":{"start":{"line":17,"column":1,"offset":2102},"end":{"line":17,"column":90,"offset":2191}}},{"type":"text","value":"\n"},{"type":"element","tagName":"h2","properties":{},"children":[{"type":"text","value":"Setting Up & Technology Stack","position":{"start":{"line":19,"column":1,"offset":2193},"end":{"line":19,"column":30,"offset":2222}}}],"position":{"start":{"line":19,"column":1,"offset":2193},"end":{"line":20,"column":30,"offset":2252}}},{"type":"text","value":"\n"},{"type":"raw","value":"<table>\n    <tbody>\n        <tr class=\"odd\">\n            <td><strong>Jekyll</strong></td>\n            <td><strong>Hugo</strong></td>\n        </tr>\n        <tr class=\"even\">\n            <td>Jekyll uses the Ruby stack.</td>\n            <td>Hugo requires the runtime for the Go programming language.</td>\n        </tr>\n        <tr class=\"odd\">\n            <td>- Large ecosystem</td>\n            <td>- Compiled language (speed)</td>\n        </tr>\n        <tr class=\"even\">\n            <td>- Multiple Ruby module installers</td>\n            <td>- Comparatively new language, smaller ecosystem</td>\n        </tr>\n        <tr class=\"odd\">\n            <td>- Developer-friendly</td>\n            <td></td>\n        </tr>\n    </tbody>\n</table>","position":{"start":{"line":22,"column":1,"offset":2254},"end":{"line":45,"column":9,"offset":2985}}},{"type":"text","value":"\n"},{"type":"element","tagName":"p","properties":{},"children":[{"type":"text","value":"Before installing your SSG, you’ll need to make sure you have all the required software. Jekyll runs on the ","position":{"start":{"line":47,"column":1,"offset":2987},"end":{"line":47,"column":109,"offset":3095}}},{"type":"element","tagName":"a","properties":{"href":"https://www.ruby-lang.org/"},"children":[{"type":"text","value":"Ruby stack","position":{"start":{"line":47,"column":110,"offset":3096},"end":{"line":47,"column":120,"offset":3106}}}],"position":{"start":{"line":47,"column":109,"offset":3095},"end":{"line":47,"column":149,"offset":3135}}},{"type":"text","value":", a popular choice for both desktop and web-based server applications. While developers enjoy Ruby for its strengths as a programming language, it can be a little difficult to manage from the user’s perspective. For example, on Linux you can install the core Ruby library using your distribution’s package manager, but additional modules can also come from Ruby’s own ","position":{"start":{"line":47,"column":149,"offset":3135},"end":{"line":47,"column":517,"offset":3503}}},{"type":"element","tagName":"strong","properties":{},"children":[{"type":"text","value":"gem","position":{"start":{"line":47,"column":519,"offset":3505},"end":{"line":47,"column":522,"offset":3508}}}],"position":{"start":{"line":47,"column":517,"offset":3503},"end":{"line":47,"column":524,"offset":3510}}},{"type":"text","value":" installer. If you don’t keep track of what came from where, you may run into issues if you upgrade from one source and not the other. All that said, if you’re a developer who works in Ruby already, the large ecosystem of Ruby software can lend some useful features to your chosen SSG.","position":{"start":{"line":47,"column":524,"offset":3510},"end":{"line":47,"column":809,"offset":3795}}}],"position":{"start":{"line":47,"column":1,"offset":2987},"end":{"line":47,"column":809,"offset":3795}}},{"type":"text","value":"\n"},{"type":"element","tagName":"p","properties":{},"children":[{"type":"element","tagName":"img","properties":{"src":"https://d33wubrfki0l68.cloudfront.net/057395ad58854b3ebafa718e7c49035e4c2765a4/b4afc/img/uploads/compare-jekyll-hugo-ruby-go.png","alt":null},"children":[],"position":{"start":{"line":49,"column":1,"offset":3797},"end":{"line":49,"column":134,"offset":3930}}}],"position":{"start":{"line":49,"column":1,"offset":3797},"end":{"line":49,"column":134,"offset":3930}}},{"type":"text","value":"\n"},{"type":"element","tagName":"p","properties":{},"children":[{"type":"text","value":"Hugo, on the other hand, is built in the ","position":{"start":{"line":51,"column":1,"offset":3932},"end":{"line":51,"column":42,"offset":3973}}},{"type":"element","tagName":"a","properties":{"href":"https://golang.org/"},"children":[{"type":"text","value":"Go programming language","position":{"start":{"line":51,"column":43,"offset":3974},"end":{"line":51,"column":66,"offset":3997}}}],"position":{"start":{"line":51,"column":42,"offset":3973},"end":{"line":51,"column":88,"offset":4019}}},{"type":"text","value":". It’s a compiled language, which means it’s very fast (compared to interpreted languages like Ruby). It’s also a relatively new language, which means the amount of additional software modules may be somewhat less compared to Ruby.","position":{"start":{"line":51,"column":88,"offset":4019},"end":{"line":51,"column":319,"offset":4250}}}],"position":{"start":{"line":51,"column":1,"offset":3932},"end":{"line":51,"column":319,"offset":4250}}},{"type":"text","value":"\n"},{"type":"element","tagName":"h2","properties":{},"children":[{"type":"text","value":"Live Reload","position":{"start":{"line":53,"column":1,"offset":4252},"end":{"line":53,"column":12,"offset":4263}}}],"position":{"start":{"line":53,"column":1,"offset":4252},"end":{"line":54,"column":12,"offset":4275}}},{"type":"text","value":"\n"},{"type":"raw","value":"<table>\n    <tbody>\n        <tr class=\"odd\">\n            <td><strong>Jekyll</strong></td>\n            <td><strong>Hugo</strong></td>\n        </tr>\n        <tr class=\"even\">\n            <td>Jekyll recently added live reload in v3.7.0 in January 2018.</td>\n            <td>Hugo has had live reload available by default for some time.</td>\n        </tr>\n    </tbody>\n</table>","position":{"start":{"line":56,"column":1,"offset":4277},"end":{"line":67,"column":9,"offset":4649}}},{"type":"text","value":"\n"},{"type":"element","tagName":"p","properties":{},"children":[{"type":"text","value":"Hugo’s web server reloads new and updated content for your site by default. In contrast, the Jekyll server offers live reload as a command-line option when you start it up:","position":{"start":{"line":69,"column":1,"offset":4651},"end":{"line":69,"column":173,"offset":4823}}}],"position":{"start":{"line":69,"column":1,"offset":4651},"end":{"line":69,"column":173,"offset":4823}}},{"type":"text","value":"\n"},{"type":"element","tagName":"pre","properties":{},"children":[{"type":"element","tagName":"code","properties":{},"children":[{"type":"text","value":"jekyll serve --livereload\n"}],"position":{"start":{"line":71,"column":1,"offset":4825},"end":{"line":71,"column":30,"offset":4854}}}],"position":{"start":{"line":71,"column":1,"offset":4825},"end":{"line":71,"column":30,"offset":4854}}},{"type":"text","value":"\n"},{"type":"element","tagName":"p","properties":{},"children":[{"type":"text","value":"Overall, this may seem like a minor inconvenience for occasional updates. But if you’re making lots of small edits, the time needed to restart your server after each one will start to add up. Keep in mind the type of site you’re looking to build when considering this point.","position":{"start":{"line":74,"column":1,"offset":4857},"end":{"line":74,"column":275,"offset":5131}}}],"position":{"start":{"line":74,"column":1,"offset":4857},"end":{"line":74,"column":275,"offset":5131}}},{"type":"text","value":"\n"},{"type":"element","tagName":"h2","properties":{},"children":[{"type":"text","value":"Content Formats","position":{"start":{"line":76,"column":1,"offset":5133},"end":{"line":76,"column":16,"offset":5148}}}],"position":{"start":{"line":76,"column":1,"offset":5133},"end":{"line":77,"column":16,"offset":5164}}},{"type":"text","value":"\n"},{"type":"raw","value":"<table>\n    <tbody>\n        <tr class=\"odd\">\n            <td><strong>Jekyll</strong></td>\n            <td><strong>Hugo</strong></td>\n        </tr>\n        <tr class=\"even\">\n            <td>Markdown and HTML by default.</td>\n            <td>Markdown by default.</td>\n        </tr>\n        <tr class=\"odd\">\n            <td>- Kramdown and Redcarpet flavors.</td>\n            <td>- Blackfriday and Mmark flavors.</td>\n        </tr>\n        <tr class=\"even\">\n            <td>- Others including AsciiDoc, reStructured Text, Org-Mode, and others via plugin</td>\n            <td>- Asciidoc and reStructred Text via \"helper\"</td>\n        </tr>\n        <td>- Pandoc support enables other inputs</td>\n        <td></td>\n    </tbody>\n</table>","position":{"start":{"line":79,"column":1,"offset":5166},"end":{"line":100,"column":9,"offset":5895}}},{"type":"text","value":"\n"},{"type":"element","tagName":"p","properties":{},"children":[{"type":"text","value":"Making sure your SSG supports your favorite input format(s) is a crucial step, since you’ll be spending the bulk of your time writing content. Both Jekyll and Hugo were built around using ","position":{"start":{"line":102,"column":1,"offset":5897},"end":{"line":102,"column":189,"offset":6085}}},{"type":"element","tagName":"a","properties":{"href":"https://daringfireball.net/projects/markdown/syntax"},"children":[{"type":"text","value":"Markdown","position":{"start":{"line":102,"column":190,"offset":6086},"end":{"line":102,"column":198,"offset":6094}}}],"position":{"start":{"line":102,"column":189,"offset":6085},"end":{"line":102,"column":252,"offset":6148}}},{"type":"text","value":" as the source format for the text for pages, posts, etc. (Your site’s graphics can be in any web-standard format, such as JPEG, PNG, and so on.)","position":{"start":{"line":102,"column":252,"offset":6148},"end":{"line":102,"column":397,"offset":6293}}}],"position":{"start":{"line":102,"column":1,"offset":5897},"end":{"line":102,"column":397,"offset":6293}}},{"type":"text","value":"\n"},{"type":"element","tagName":"p","properties":{},"children":[{"type":"element","tagName":"img","properties":{"src":"https://d33wubrfki0l68.cloudfront.net/96eda94d48631905e9a62f074200ded97f78294b/337ba/img/uploads/compare-jekyll-hugo-markdown.png","alt":null},"children":[],"position":{"start":{"line":104,"column":1,"offset":6295},"end":{"line":104,"column":135,"offset":6429}}}],"position":{"start":{"line":104,"column":1,"offset":6295},"end":{"line":104,"column":135,"offset":6429}}},{"type":"text","value":"\n"},{"type":"element","tagName":"p","properties":{},"children":[{"type":"text","value":"Either app is also capable of handling content in other formats via built-in functions, plugins, or external programs. Note here that Hugo’s support for ","position":{"start":{"line":106,"column":1,"offset":6431},"end":{"line":106,"column":154,"offset":6584}}},{"type":"element","tagName":"a","properties":{"href":"https://pandoc.org/"},"children":[{"type":"text","value":"Pandoc","position":{"start":{"line":106,"column":155,"offset":6585},"end":{"line":106,"column":161,"offset":6591}}}],"position":{"start":{"line":106,"column":154,"offset":6584},"end":{"line":106,"column":183,"offset":6613}}},{"type":"text","value":" gives you a wide array of input options, including word processing formats like .DOCX or .ODT.","position":{"start":{"line":106,"column":183,"offset":6613},"end":{"line":106,"column":278,"offset":6708}}}],"position":{"start":{"line":106,"column":1,"offset":6431},"end":{"line":106,"column":278,"offset":6708}}},{"type":"text","value":"\n"},{"type":"element","tagName":"h2","properties":{},"children":[{"type":"text","value":"Themes & Templating","position":{"start":{"line":108,"column":1,"offset":6710},"end":{"line":108,"column":20,"offset":6729}}}],"position":{"start":{"line":108,"column":1,"offset":6710},"end":{"line":109,"column":20,"offset":6749}}},{"type":"text","value":"\n"},{"type":"raw","value":"<table>\n    <tbody>\n        <tr class=\"odd\">\n            <td><strong>Jekyll</strong></td>\n            <td><strong>Hugo</strong></td>\n        </tr>\n        <tr class=\"even\">\n            <td>Jekyll uses the Liquid templating engine</td>\n            <td>Hugo uses the Go programming language's internal templates.</td>\n        </tr>\n    </tbody>\n</table>","position":{"start":{"line":111,"column":1,"offset":6751},"end":{"line":122,"column":9,"offset":7102}}},{"type":"text","value":"\n"},{"type":"element","tagName":"p","properties":{},"children":[{"type":"text","value":"Both Jekyll and Hugo have alternate themes available – the ","position":{"start":{"line":124,"column":1,"offset":7104},"end":{"line":124,"column":60,"offset":7163}}},{"type":"element","tagName":"a","properties":{"href":"http://jekyllthemes.org/"},"children":[{"type":"text","value":"Jekyll Themes","position":{"start":{"line":124,"column":61,"offset":7164},"end":{"line":124,"column":74,"offset":7177}}}],"position":{"start":{"line":124,"column":60,"offset":7163},"end":{"line":124,"column":101,"offset":7204}}},{"type":"text","value":" site lists them in various categories, while the ","position":{"start":{"line":124,"column":101,"offset":7204},"end":{"line":124,"column":151,"offset":7254}}},{"type":"element","tagName":"a","properties":{"href":"https://themes.gohugo.io/"},"children":[{"type":"text","value":"Themes section of the official Hugo site","position":{"start":{"line":124,"column":152,"offset":7255},"end":{"line":124,"column":192,"offset":7295}}}],"position":{"start":{"line":124,"column":151,"offset":7254},"end":{"line":124,"column":220,"offset":7323}}},{"type":"text","value":" has them tagged as well. However, many of these are relatively simple themes (consider the example at the top-right below), and themes are not compatible across different SSGs. So if you like a Jekyll theme but the functionality of Hugo, you’re out of luck.","position":{"start":{"line":124,"column":220,"offset":7323},"end":{"line":124,"column":478,"offset":7581}}}],"position":{"start":{"line":124,"column":1,"offset":7104},"end":{"line":124,"column":478,"offset":7581}}},{"type":"text","value":"\n"},{"type":"element","tagName":"p","properties":{},"children":[{"type":"element","tagName":"img","properties":{"src":"https://d33wubrfki0l68.cloudfront.net/ec138f2f7087329e7368e72fb66dafc241915f9e/f5a29/img/uploads/compare-jekyll-hugo-theme.png","alt":null},"children":[],"position":{"start":{"line":126,"column":1,"offset":7583},"end":{"line":126,"column":132,"offset":7714}}}],"position":{"start":{"line":126,"column":1,"offset":7583},"end":{"line":126,"column":132,"offset":7714}}},{"type":"text","value":"\n"},{"type":"element","tagName":"p","properties":{},"children":[{"type":"text","value":"The template language describes how the HTML files are constructed from source content. For example, when you write a post for Jekyll in Markdown, you don’t include the things that will be included in the header of the resulting site, such as the menu. Rather, these are gathered from other files, and the template defines how they’re all glued together. This is easy to see in the below image, which illustrates a simple template for Hugo.","position":{"start":{"line":128,"column":1,"offset":7716},"end":{"line":128,"column":441,"offset":8156}}}],"position":{"start":{"line":128,"column":1,"offset":7716},"end":{"line":128,"column":441,"offset":8156}}},{"type":"text","value":"\n"},{"type":"element","tagName":"p","properties":{},"children":[{"type":"element","tagName":"img","properties":{"src":"https://d33wubrfki0l68.cloudfront.net/1df79c7b902625c90c4de72a1fd0605bd4931556/43927/img/uploads/compare-jekyll-hugo-template.png","alt":null},"children":[],"position":{"start":{"line":130,"column":1,"offset":8158},"end":{"line":130,"column":135,"offset":8292}}}],"position":{"start":{"line":130,"column":1,"offset":8158},"end":{"line":130,"column":135,"offset":8292}}},{"type":"text","value":"\n"},{"type":"element","tagName":"p","properties":{},"children":[{"type":"text","value":"Most casual users won’t ever use these. They’ll either use the templates built into the theme they’ve selected, or download a plugin that provides new templates. They may actually just download a template file and drop it in the appropriate folder. But if you already use one of these languages, you’ll find it that much easier to create your own SSG templates.","position":{"start":{"line":132,"column":1,"offset":8294},"end":{"line":132,"column":362,"offset":8655}}}],"position":{"start":{"line":132,"column":1,"offset":8294},"end":{"line":132,"column":362,"offset":8655}}},{"type":"text","value":"\n"},{"type":"element","tagName":"h2","properties":{},"children":[{"type":"text","value":"Plug-in Support","position":{"start":{"line":134,"column":1,"offset":8657},"end":{"line":134,"column":16,"offset":8672}}}],"position":{"start":{"line":134,"column":1,"offset":8657},"end":{"line":135,"column":16,"offset":8688}}},{"type":"text","value":"\n"},{"type":"raw","value":"<table>\n    <tbody>\n        <tr class=\"odd\">\n            <td><strong>Jekyll</strong></td>\n            <td><strong>Hugo</strong></td>\n        </tr>\n        <tr class=\"even\">\n            <td>Jekyll has a large collection of plugins.</td>\n            <td>Hugo does not have a plugin mechanism.</td>\n        </tr>\n    </tbody>\n</table>","position":{"start":{"line":137,"column":1,"offset":8690},"end":{"line":148,"column":9,"offset":9021}}},{"type":"text","value":"\n"},{"type":"element","tagName":"p","properties":{},"children":[{"type":"text","value":"Static sites lend themselves well to simple publications consisting of text and graphics. But at some point, you’re likely to want to add some sort of functionality to your site, such as a form to sign up for your newsletter. This is where plugins can help you. Unlike the CMS standard WordPress, however, there’s not a nicely formatted collection of plugins for static site generators. Instead, you’ll need to hunt down the plugin you want, download it, and install it. Installation will likely be unzipping the plugin into an appropriate folder, and tweaking your config files to turn it on.","position":{"start":{"line":150,"column":1,"offset":9023},"end":{"line":150,"column":594,"offset":9616}}}],"position":{"start":{"line":150,"column":1,"offset":9023},"end":{"line":150,"column":594,"offset":9616}}},{"type":"text","value":"\n"},{"type":"element","tagName":"p","properties":{},"children":[{"type":"text","value":"Jekyll has arguably the larger collection of available plugins, as it’s been around longer, and provides developers a nice API to work with. Ruby developers are also a bit more common (for now). The ","position":{"start":{"line":152,"column":1,"offset":9618},"end":{"line":152,"column":200,"offset":9817}}},{"type":"element","tagName":"a","properties":{"href":"https://github.com/planetjekyll/awesome-jekyll-plugins"},"children":[{"type":"text","value":"“Awesome Jekyll Plugins”","position":{"start":{"line":152,"column":201,"offset":9818},"end":{"line":152,"column":225,"offset":9842}}}],"position":{"start":{"line":152,"column":200,"offset":9817},"end":{"line":152,"column":282,"offset":9899}}},{"type":"text","value":" page on GitHub provides a nicely curated list of plugins, broken down by category.","position":{"start":{"line":152,"column":282,"offset":9899},"end":{"line":152,"column":365,"offset":9982}}}],"position":{"start":{"line":152,"column":1,"offset":9618},"end":{"line":152,"column":365,"offset":9982}}},{"type":"text","value":"\n"},{"type":"element","tagName":"p","properties":{},"children":[{"type":"text","value":"On the other hand, Hugo doesn’t support a full-featured plugin mechanism. There are some utilities that can be used to enhance the base Hugo install, such as the ","position":{"start":{"line":154,"column":1,"offset":9984},"end":{"line":154,"column":163,"offset":10146}}},{"type":"element","tagName":"a","properties":{"href":"https://github.com/icecreammatt/hugo-gallery"},"children":[{"type":"text","value":"Hugo Gallery Generator","position":{"start":{"line":154,"column":164,"offset":10147},"end":{"line":154,"column":186,"offset":10169}}}],"position":{"start":{"line":154,"column":163,"offset":10146},"end":{"line":154,"column":233,"offset":10216}}},{"type":"text","value":" tool. But if you’re someone who used to go crazy trying out lots of WordPress plugins, Hugo might not be your best choice.","position":{"start":{"line":154,"column":233,"offset":10216},"end":{"line":154,"column":356,"offset":10339}}}],"position":{"start":{"line":154,"column":1,"offset":9984},"end":{"line":154,"column":356,"offset":10339}}},{"type":"text","value":"\n"},{"type":"element","tagName":"h2","properties":{},"children":[{"type":"text","value":"Administration","position":{"start":{"line":156,"column":1,"offset":10341},"end":{"line":156,"column":15,"offset":10355}}}],"position":{"start":{"line":156,"column":1,"offset":10341},"end":{"line":157,"column":15,"offset":10370}}},{"type":"text","value":"\n"},{"type":"raw","value":"<table>\n    <tbody>\n        <tr class=\"odd\">\n            <td><strong>Jekyll</strong></td>\n            <td><strong>Hugo</strong></td>\n        </tr>\n        <tr class=\"even\">\n            <td>A wide variety of admin panels are compatible with Jekyll.</td>\n            <td>Hugo also has dozens of admin options, both open and closed source.</td>\n        </tr>\n    </tbody>\n</table>","position":{"start":{"line":159,"column":1,"offset":10372},"end":{"line":170,"column":9,"offset":10749}}},{"type":"text","value":"\n"},{"type":"element","tagName":"p","properties":{},"children":[{"type":"text","value":"While the text- and console-based nature of SSGs are among their greatest advantages, there are lots of reasons you might want to add a UI. You may have an editorial team working on your site with you. You may need to make a change to the site while you’re away from your computer. Fortunately, SSGs and their admin panels aren’t married, giving you a level of flexibility in authoring and workflow you can’t find with a traditional CMS.","position":{"start":{"line":172,"column":1,"offset":10751},"end":{"line":172,"column":438,"offset":11188}}}],"position":{"start":{"line":172,"column":1,"offset":10751},"end":{"line":172,"column":438,"offset":11188}}},{"type":"text","value":"\n"},{"type":"element","tagName":"p","properties":{},"children":[{"type":"element","tagName":"img","properties":{"src":"https://d33wubrfki0l68.cloudfront.net/435a674323dc4470ed9518facf1f93e8abe88897/42812/img/uploads/compare-jekyll-hugo-admin.png","alt":null},"children":[],"position":{"start":{"line":174,"column":1,"offset":11190},"end":{"line":174,"column":132,"offset":11321}}}],"position":{"start":{"line":174,"column":1,"offset":11190},"end":{"line":174,"column":132,"offset":11321}}},{"type":"text","value":"\n"},{"type":"element","tagName":"p","properties":{},"children":[{"type":"text","value":"Support for an administrative UI is just a function of finding one that supports your selected SSG. Jekyll or Hugo know nothing about the “headless CMS” that may (or may not) sit next to it, allowing you to do WYSIWYG editing. It’s the admin panel that needs support for the SSG, so it knows how to read the content, how to build the updated site, etc. The site ","position":{"start":{"line":176,"column":1,"offset":11323},"end":{"line":176,"column":363,"offset":11685}}},{"type":"element","tagName":"a","properties":{"href":"https://headlesscms.org/"},"children":[{"type":"text","value":"HeadlessCMS.org","position":{"start":{"line":176,"column":364,"offset":11686},"end":{"line":176,"column":379,"offset":11701}}}],"position":{"start":{"line":176,"column":363,"offset":11685},"end":{"line":176,"column":406,"offset":11728}}},{"type":"text","value":" is pretty much ","position":{"start":{"line":176,"column":406,"offset":11728},"end":{"line":176,"column":422,"offset":11744}}},{"type":"element","tagName":"strong","properties":{},"children":[{"type":"text","value":"the","position":{"start":{"line":176,"column":424,"offset":11746},"end":{"line":176,"column":427,"offset":11749}}}],"position":{"start":{"line":176,"column":422,"offset":11744},"end":{"line":176,"column":429,"offset":11751}}},{"type":"text","value":" place to search out these admin UIs, and provides you with a nice rundown of what you need to run it, and what SSGs it supports.","position":{"start":{"line":176,"column":429,"offset":11751},"end":{"line":176,"column":558,"offset":11880}}}],"position":{"start":{"line":176,"column":1,"offset":11323},"end":{"line":176,"column":558,"offset":11880}}},{"type":"text","value":"\n"},{"type":"element","tagName":"h2","properties":{},"children":[{"type":"text","value":"Conclusion","position":{"start":{"line":178,"column":1,"offset":11882},"end":{"line":178,"column":11,"offset":11892}}}],"position":{"start":{"line":178,"column":1,"offset":11882},"end":{"line":179,"column":11,"offset":11903}}},{"type":"text","value":"\n"},{"type":"element","tagName":"p","properties":{},"children":[{"type":"text","value":"To wrap up, there are a few key attributes to consider when selecting an SSG, summarized in the following table:","position":{"start":{"line":181,"column":1,"offset":11905},"end":{"line":181,"column":113,"offset":12017}}}],"position":{"start":{"line":181,"column":1,"offset":11905},"end":{"line":181,"column":113,"offset":12017}}},{"type":"text","value":"\n"},{"type":"raw","value":"<table>\n    <tbody>\n        <tr class=\"odd\">\n            <td></td>\n            <td><strong>Jekyll</strong></td>\n            <td><strong>Hugo</strong></td>\n        </tr>\n        <tr class=\"even\">\n            <td>Technology Stack</td>\n            <td>Jekyll uses the Ruby stack.</td>\n            <td>Hugo requires the runtime for the Go programming language.</td>\n        </tr>\n        <tr class=\"odd\">\n            <td></td>\n            <td>- Large ecosystem</td>\n            <td>- Compiled language (speed)</td>\n        </tr>\n        <tr class=\"even\">\n            <td></td>\n            <td>- Multiple Ruby module installers</td>\n            <td>- Comparatively new language, smaller ecosystem</td>\n        </tr>\n        <tr class=\"odd\">\n            <td></td>\n            <td>- Developer-friendly</td>\n            <td></td>\n        </tr>\n        <tr class=\"even\">\n            <td>Live Reload</td>\n            <td>Jekyll recently added live reload in v3.7.0 in January 2018.</td>\n            <td>Hugo has had live reload available for some time.</td>\n        </tr>\n        <tr class=\"odd\">\n            <td>Input Formats</td>\n            <td>Markdown and HTML by default.</td>\n            <td>Markdown by default.</td>\n        </tr>\n        <tr class=\"even\">\n            <td></td>\n            <td>- Kramdown and Redcarpet flavors.</td>\n            <td>- Blackfriday and Mmark flavors.</td>\n        </tr>\n        <tr class=\"odd\">\n            <td></td>\n            <td>- Others including AsciiDoc, reStructured Text, Org-Mode, and others via plugin</td>\n            <td>- Asciidoc and reStructred Text via \"helper\"</td>\n        </tr>\n        <tr class=\"even\">\n            <td></td>\n            <td>- Pandoc support enables other inputs</td>\n            <td></td>\n        </tr>\n        <tr class=\"odd\">\n            <td>Templating/Theming</td>\n            <td>- Jekyll uses the Liquid templating engine</td>\n            <td>- Hugo uses the Go programming language's internal templates.</td>\n        </tr>\n        <tr class=\"even\">\n            <td></td>\n            <td>- A large collection of themes are available.</td>\n            <td>- While not quite as many as Jekyll, Hugo has plenty of themes available.</td>\n        </tr>\n        <tr class=\"odd\">\n            <td>Administration</td>\n            <td>A wide variety of admin panels are compatible with Jekyll.</td>\n            <td>Hugo also has dozens of admin options, both open and closed source.</td>\n        </tr>\n    </tbody>\n</table>","position":{"start":{"line":183,"column":1,"offset":12019},"end":{"line":251,"column":9,"offset":14505}}},{"type":"text","value":"\n"},{"type":"element","tagName":"p","properties":{},"children":[{"type":"text","value":"Armed with this knowledge, you’re now in a great position to go install one (or both!) of these and give them a whirl. You never know, their simplicity and elegance may surprise you.","position":{"start":{"line":253,"column":1,"offset":14507},"end":{"line":253,"column":183,"offset":14689}}}],"position":{"start":{"line":253,"column":1,"offset":14507},"end":{"line":253,"column":183,"offset":14689}}}],"position":{"start":{"line":1,"column":1,"offset":0},"end":{"line":254,"column":1,"offset":14690}}}}